irekia/__init__.py
irekia/client.py
irekia/data/metadata.json
irekia-0.1.2.dist-info/METADATA
irekia-0.1.2.dist-info/RECORD
irekia-0.1.2.dist-info/WHEEL
irekia-0.1.2.dist-info/top_level.txt
