Metadata-Version: 2.1
Name: irekia
Version: 0.1.2
Summary: Python client for the Open Data Euskadi REST API.
Home-page: https://github.com/eillarra/irekia
Author: eillarra
Author-email: eneko@illarra.com
License: MIT
Project-URL: Code, https://github.com/eillarra/irekia
Project-URL: Issues, https://github.com/eillarra/irekia/issues
Keywords: opendata api euskadi
Platform: UNKNOWN
Classifier: Development Status :: 3 - Alpha
Classifier: Environment :: Web Environment
Classifier: Intended Audience :: Developers
Classifier: License :: OSI Approved :: MIT License
Classifier: Operating System :: OS Independent
Classifier: Programming Language :: Python
Classifier: Programming Language :: Python :: 2.7
Classifier: Programming Language :: Python :: 3.6
Classifier: Topic :: Internet :: WWW/HTTP :: Dynamic Content
Classifier: Topic :: Software Development :: Libraries :: Python Modules
Requires-Dist: requests
